[{"id":"b12cb68d.009728","type":"tab","label":"Flow 1","disabled":false,"info":""},{"id":"9f9cfd71.f17c9","type":"ui_tab","z":"","name":"Customer Care Helpdesk","icon":"dashboard","disabled":false,"hidden":false},{"id":"1d37698b.10f256","type":"ui_group","z":"","name":"Chatbot","tab":"9f9cfd71.f17c9","order":1,"disp":true,"width":15,"collapse":false},{"id":"7428e36d.b50bec","type":"ui_base","theme":{"name":"theme-dark","lightTheme":{"default":"#0094CE","baseColor":"#0094CE","baseFont":"-apple-system,BlinkMacSystemFont,Segoe UI,Roboto,Oxygen-Sans,Ubuntu,Cantarell,Helvetica Neue,sans-serif","edited":true,"reset":false},"darkTheme":{"default":"#097479","baseColor":"#5a37d7","baseFont":"Trebuchet MS,Helvetica,sans-serif","edited":true,"reset":false},"customTheme":{"name":"Untitled Theme 1","default":"#4B7930","baseColor":"#4B7930","baseFont":"-apple-system,BlinkMacSystemFont,Segoe UI,Roboto,Oxygen-Sans,Ubuntu,Cantarell,Helvetica Neue,sans-serif"},"themeState":{"base-color":{"default":"#097479","value":"#5a37d7","edited":true},"page-titlebar-backgroundColor":{"value":"#5a37d7","edited":false},"page-backgroundColor":{"value":"#111111","edited":false},"page-sidebar-backgroundColor":{"value":"#000000","edited":false},"group-textColor":{"value":"#8f77e4","edited":false},"group-borderColor":{"value":"#555555","edited":false},"group-backgroundColor":{"value":"#333333","edited":false},"widget-textColor":{"value":"#eeeeee","edited":false},"widget-backgroundColor":{"value":"#5a37d7","edited":false},"widget-borderColor":{"value":"#333333","edited":false},"base-font":{"value":"Trebuchet MS,Helvetica,sans-serif"}},"angularTheme":{"primary":"indigo","accents":"indigo","warn":"red","background":"teal","palette":"light"}},"site":{"name":"Node-RED Dashboard","hideToolbar":"false","allowSwipe":"false","lockMenu":"false","allowTempTheme":"none","dateFormat":"DD/MM/YYYY","sizes":{"sx":20,"sy":47,"gx":13,"gy":13,"cx":37,"cy":37,"px":13,"py":13}}},{"id":"c4eb101b.f2e47","type":"ui_group","name":"Group 1","tab":"","order":1,"disp":true,"width":6},{"id":"d0803bac.5a7c88","type":"ui_group","name":"Group 2","tab":"","order":2,"disp":true,"width":6},{"id":"63d052f0.13165c","type":"ui_group","name":"Group 3","tab":"","order":3,"disp":true,"width":6},{"id":"71f1aea9.35b1f","type":"ui_form","z":"b12cb68d.009728","name":"","label":"","group":"1d37698b.10f256","order":1,"width":0,"height":0,"options":[{"label":"Enter your input","value":"text","type":"text","required":true,"rows":null}],"formValue":{"text":""},"payload":"","submit":"Enter","cancel":"Cancel","topic":"","x":70,"y":160,"wires":[["c4924e77.7625b"]]},{"id":"c4924e77.7625b","type":"function","z":"b12cb68d.009728","name":"","func":"msg.payload=msg.payload.text;\nreturn msg;","outputs":1,"noerr":0,"x":210,"y":160,"wires":[["27f06fe6.09e8d","c158d2bb.a2cd9"]]},{"id":"a23e58b9.62dde8","type":"function","z":"b12cb68d.009728","name":"","func":"msg.payload=msg.payload.output.text[0];\nreturn msg;","outputs":1,"noerr":0,"x":470,"y":160,"wires":[["1653fd6d.d60453"]]},{"id":"c158d2bb.a2cd9","type":"watson-conversation-v1","z":"b12cb68d.009728","name":"Customer Care","workspaceid":"e92b582f-e3ca-4fb6-9c45-1650cd720673","multiuser":false,"context":true,"empty-payload":false,"service-endpoint":"https://api.eu-gb.assistant.watson.cloud.ibm.com/instances/6160ac20-8d2c-42d1-833e-44a39f8c423b","timeout":"","optout-learning":false,"x":300,"y":60,"wires":[["c3d71bd2.801808","a23e58b9.62dde8"]]},{"id":"27f06fe6.09e8d","type":"ui_text","z":"b12cb68d.009728","group":"1d37698b.10f256","order":2,"width":0,"height":0,"name":"","label":"You:","format":"{{msg.payload}}","layout":"col-center","x":270,"y":260,"wires":[]},{"id":"c3d71bd2.801808","type":"debug","z":"b12cb68d.009728","name":"","active":true,"tosidebar":true,"console":false,"tostatus":false,"complete":"false","x":610,"y":60,"wires":[]},{"id":"1653fd6d.d60453","type":"ui_text","z":"b12cb68d.009728","group":"1d37698b.10f256","order":3,"width":"15","height":"2","name":"","label":"Bot:","format":"{{msg.payload}}","layout":"col-center","x":570,"y":260,"wires":[]}]